decision_tree_matott/__init__.py
decision_tree_matott/rule.py
decision_tree_matott/tree.py
decision_tree_matott-0.3.0.dist-info/METADATA
decision_tree_matott-0.3.0.dist-info/WHEEL
decision_tree_matott-0.3.0.dist-info/licenses/LICENSE
decision_tree_matott-0.3.0.dist-info/RECORD
